[
  {
    "name": "Diamond",
    "entityId": "Entity0.7571396098054197",
    "type": "fixed",
    "path": "Diamond",
    "position": [
      0,
      1.5,
      0
    ],
    "rotation": [
      0.46945181488990784,
      0.11821052432060242,
      -0.5619106888771057
    ],
    "scale": [
      1,
      1,
      1
    ]
  },
  {
    "name": "KillBrick",
    "entityId": "Entity0.12389176198117624",
    "type": "dynamic",
    "path": "KillBrick",
    "position": [
      10,
      2.5,
      4
    ],
    "rotation": [
      -0.4203973412513733,
      0.6892281174659729,
      -0.5881372690200806
    ],
    "scale": [
      1,
      1,
      1
    ]
  }
]